wallpaperscraft/__init__.py
wallpaperscraft/api.py
wallpaperscraft/asyncapi.py
wallpaperscraft/types.py
wallpaperscraft-1.0.2.dist-info/LICENSE
wallpaperscraft-1.0.2.dist-info/METADATA
wallpaperscraft-1.0.2.dist-info/WHEEL
wallpaperscraft-1.0.2.dist-info/top_level.txt
wallpaperscraft-1.0.2.dist-info/RECORD
