Metadata-Version: 2.1
Name: wallpaperscraft
Version: 1.0.2
Summary: Unofficial API WallpapersCraft (wallpaperscraft.com)
Home-page: https://github.com/Den4ikSuperOstryyPer4ik/WallpapersCraftAPI/
Download-URL: https://github.com/Den4ikSuperOstryyPer4ik/WallpapersCraftAPI//releases/latest
Author: Den4ikSuperOstryyPer4ik
License: Apache2.0
Keywords: python3 wallpaperscraft wallpapers craft WallpapersCraftAPI
Classifier: Programming Language :: Python :: 3.11
Classifier: Programming Language :: Python :: 3.10
Classifier: Programming Language :: Python :: 3.9
Requires-Python: >=3.7
License-File: LICENSE
Requires-Dist: bs4
Requires-Dist: requests
Requires-Dist: aiohttp
Requires-Dist: pydantic
